mediux_posters/__init__.py
mediux_posters/__main__.py
mediux_posters/console.py
mediux_posters/mediux.py
mediux_posters/settings.py
mediux_posters/utils.py
mediux_posters/services/__init__.py
mediux_posters/services/_base.py
mediux_posters/services/jellyfin.py
mediux_posters/services/plex.py
mediux_posters-0.4.2.dist-info/METADATA
mediux_posters-0.4.2.dist-info/WHEEL
mediux_posters-0.4.2.dist-info/entry_points.txt
mediux_posters-0.4.2.dist-info/licenses/LICENSE
mediux_posters-0.4.2.dist-info/RECORD
