Metadata-Version: 2.4
Name: mediux-posters
Version: 0.4.2
Summary: Fetches Show, Movie, and Collection cover art from Mediux and updates Plex/Jellyfin using TMDB IDs.
Project-URL: Homepage, https://pypi.org/project/Mediux-Posters
Project-URL: Issues, https://github.com/Buried-In-Code/Mediux-Posters/issues
Project-URL: Source, https://github.com/Buried-In-Code/Mediux-Posters
Author-email: BuriedInCode <BuriedInCode@tuta.io>
License: MIT
License-File: LICENSE
Classifier: Development Status :: 4 - Beta
Classifier: Environment :: Console
Classifier: License :: OSI Approved :: MIT License
Classifier: Natural Language :: English
Classifier: Operating System :: MacOS
Classifier: Operating System :: Microsoft :: Windows
Classifier: Operating System :: POSIX :: Linux
Classifier: Programming Language :: Python :: 3.10
Classifier: Programming Language :: Python :: 3.11
Classifier: Programming Language :: Python :: 3.12
Classifier: Programming Language :: Python :: 3.13
Classifier: Typing :: Typed
Requires-Python: >=3.10
Requires-Dist: beautifulsoup4>=4.13.3
Requires-Dist: plexapi>=4.16.1
Requires-Dist: pydantic>=2.11.1
Requires-Dist: requests>=2.32.3
Requires-Dist: rich>=14.0.0
Requires-Dist: tomli-w>=1.2.0
Requires-Dist: tomli>=2.2.1; python_version < '3.11'
Requires-Dist: typer>=0.15.2
